[
    {
        "NatEmis": 700240499,
        "ProvinceCD": 7,
        "Province": "GT",
        "Institution_Name": "A RE THABENG PRIMARY SCHOOL",
        "Status": "OPEN",
        "Sector": "PUBLIC",
        "Type_DoE": "ORDINARY SCHOOL",
        "Phase": "PRIMARY SCHOOL",
        "Specialization": "ORDINARY",
        "OwnerLand": "PUBLIC",
        "OwnerBuild": "PUBLIC",
        "Ownership": "STATE",
        "ExDept": "DEPARTMENT OF EDUCATION AND TRAINING(DET)",
        "PaypointNo": "915042",
        "ComponentNo": "915042",
        "ExamNo": "99",
        "GIS_Longitude": "28.10581969",
        "GIS_Latitude": "-25.54234622",
        "GISSource": "GISSource",
        "Magisterial_District": "99",
        "DMunName": "CITY OF TSHWANE METROPOLITAN MUNICIPALITY",
        "LMunName": "CITY OF TSHWANE METROPOLITAN MUNICIPALITY",
        "Ward_ID": "79900036",
        "EIRegion": "TSHWAGA",
        "EIDistrict": "TSHWANE WEST",
        "EICircuit": "TW_3",
        "Addressee": "MM MOLESHIWA",
        "Township_Village": "SOSHANGUVE",
        "Suburb": "PRETORIA",
        "Town_City": "PRETORIA",
        "StreetAddress": "1670 BLOCK L, SOSHANGUVE, PRETORIA, 0152",
        "PostalAddress": "PO BOX 23, SOSHANGUVE, 0164",
        "Telephone": "0127972726",
        "Facsimile": "0127972726",
        "cellno": "0825540329",
        "E_Mail": "240499@ananzi.co.za",
        "Section21": "YES",
        "Section21_Funct": "AC",
        "Quintile": "3",
        "NAS": "N",
        "NodalArea": "NOT APPLICABLE",
        "NoFeeSchool": "YES",
        "Allocation": "99",
        "Urban_Rural": "URBAN",
        "Open_Boarding_school": "NO",
        "ANA_School": "YES",
        "Full_Service_School": "NO",
        "School_Prototype_size": "Large "
    },
    {
        "NatEmis": 700270595,
        "ProvinceCD": 7,
        "Province": "GT",
        "Institution_Name": "AB PHOKOMPE SECONDARY SCHOOL",
        "Status": "OPEN",
        "Sector": "PUBLIC",
        "Type_DoE": "ORDINARY SCHOOL",
        "Phase": "SECONDARY SCHOOL",
        "Specialization": "ORDINARY",
        "OwnerLand": "PUBLIC",
        "OwnerBuild": "PUBLIC",
        "Ownership": "STATE",
        "ExDept": "DEPARTMENT OF EDUCATION AND TRAINING(DET)",
        "PaypointNo": "902009",
        "ComponentNo": "902009",
        "ExamNo": "8270595",
        "ExamCentre": "AB PHOKOMPE SECONDARY SCHOOL",
        "GIS_Longitude": "27.70310679",
        "GIS_Latitude": "-26.22405571",
        "GISSource": "GISSource",
        "Magisterial_District": "99",
        "DMunName": "WEST RAND DISTRICT MUNICIPALITY",
        "LMunName": "RANDFONTEIN LOCAL MUNICIPALITY",
        "Ward_ID": "74802019",
        "EIRegion": "TSHWAGA",
        "EIDistrict": "GAUTENG WEST",
        "EICircuit": "GW_3",
        "Addressee": "EK SHELA",
        "Township_Village": "MOHLAKENG",
        "Suburb": "MOHLAKENG ",
        "Town_City": "JOHANNESBURG",
        "StreetAddress": "7440 SEME, MOHLAKENG, RANDFONTEIN, 1759",
        "PostalAddress": "1, MOHLAKENG, 1759",
        "Telephone": "0114140002",
        "Facsimile": "0114140007",
        "cellno": "0825536025",
        "E_Mail": "eshela1@gamil.com",
        "Section21": "YES",
        "Section21_Funct": "ACD",
        "Quintile": "4",
        "NAS": "N",
        "NodalArea": "NOT APPLICABLE",
        "NoFeeSchool": "NO",
        "Allocation": "99",
        "Urban_Rural": "URBAN",
        "Open_Boarding_school": "NO",
        "ANA_School": "YES",
        "Full_Service_School": "NO",
        "School_Prototype_size": "Xlarge"
    },
    {
        "NatEmis": 700131805,
        "ProvinceCD": 7,
        "Province": "GT",
        "Institution_Name": "AB XUMA PRIMARY SCHOOL",
        "Status": "OPEN",
        "Sector": "PUBLIC",
        "Type_DoE": "ORDINARY SCHOOL",
        "Phase": "PRIMARY SCHOOL",
        "Specialization": "ORDINARY",
        "OwnerLand": "PUBLIC",
        "OwnerBuild": "PUBLIC",
        "Ownership": "STATE",
        "ExDept": "DEPARTMENT OF EDUCATION AND TRAINING(DET)",
        "PaypointNo": "910010",
        "ComponentNo": "910010",
        "ExamNo": "99",
        "GIS_Longitude": "27.9200466662",
        "GIS_Latitude": "-26.2348250001",
        "GISSource": "GISSource",
        "Magisterial_District": "99",
        "DMunName": "CITY OF JOHANNESBURG METROPOLITAN MUNICIPALITY",
        "LMunName": "CITY OF JOHANNESBURG METROPOLITAN MUNICIPALITY",
        "Ward_ID": "79800031",
        "EIRegion": "JOHANNESBURG",
        "EIDistrict": "JOHANNESBURG NORTH",
        "EICircuit": "JN_2",
        "Addressee": "SDM MALINGA",
        "Township_Village": "ORLANDO EAST",
        "Suburb": "ORLANDO EAST",
        "Town_City": "JOHANNESBURG",
        "StreetAddress": "6565 MOOKI STREET, ORLANDO EAST, SOWETO, 1804",
        "PostalAddress": "P.O. BOX 63, ORLANDO, 1803",
        "Telephone": "0119351089",
        "Facsimile": "0119352909",
        "cellno": "0825533494",
        "E_Mail": "abxuma@telkomsa.net",
        "Section21": "YES",
        "Section21_Funct": "ACD",
        "Quintile": "3",
        "NAS": "N",
        "NodalArea": "NOT APPLICABLE",
        "NoFeeSchool": "YES",
        "Allocation": "99",
        "Urban_Rural": "URBAN",
        "Open_Boarding_school": "NO",
        "ANA_School": "YES",
        "Full_Service_School": "NO",
        "School_Prototype_size": "Large "
    },
    {
        "NatEmis": 700400788,
        "ProvinceCD": 7,
        "Province": "GT",
        "Institution_Name": "ABBOTTS COLLEGE-CENTURION",
        "Status": "CLOSED",
        "Sector": "INDEPENDENT",
        "Type_DoE": "ORDINARY SCHOOL",
        "Phase": "SECONDARY SCHOOL",
        "Specialization": "ORDINARY",
        "Ownership": "INDEPENDENT",
        "ExDept": "NEW EDUCATION DEPARTMENT",
        "PaypointNo": "99",
        "ComponentNo": "99",
        "ExamNo": "99",
        "GISSource": "GISSource",
        "Magisterial_District": "99",
        "Ward_ID": "99",
        "EIRegion": "TSHWAGA",
        "EIDistrict": "TSHWANE SOUTH",
        "EICircuit": "TS_",
        "Addressee": " ",
        "Town_City": "PRETORIA",
        "StreetAddress": "68 OAK AVENUE, HIGHVELD TECHNO PARK, CENTURION, ",
        "PostalAddress": ", , ",
        "Telephone": "0126653144",
        "Facsimile": "99",
        "cellno": "99",
        "E_Mail": "centurion@abbotts.co.za",
        "Section21": "NOT APPLICABLE",
        "Section21_Funct": "NOT APPLICABLE",
        "Quintile": "NOT APPLICABLE",
        "NAS": "N",
        "NodalArea": "NOT APPLICABLE",
        "NoFeeSchool": "NOT APPLICABLE",
        "Allocation": "0",
        "Urban_Rural": "URBAN",
        "Open_Boarding_school": "NO",
        "ANA_School": "NO",
        "Full_Service_School": "NO",
        "School_Prototype_size": "TO BE UPDATED"
    }
]